MANIFEST.in
README.rst
setup.cfg
setup.py
tests/__init__.py
tests/test_gb_ecsl.py
tests/test_gb_moss.py
tests/test_vies.py
tests/test_vrws.py
tests/metaphone/__init__.py
tests/metaphone/test_metaphone.py
tests/metaphone/test_word.py
vat/__init__.py
vat/addresscmp.py
vat/memberstate.py
vat/rates.py
vat/vat_check.py
vat/vies.py
vat/vrws.py
vat.egg-info/PKG-INFO
vat.egg-info/SOURCES.txt
vat.egg-info/dependency_links.txt
vat.egg-info/requires.txt
vat.egg-info/top_level.txt
vat/gb/__init__.py
vat/gb/ecsl.py
vat/gb/moss/__init__.py
vat/gb/moss/genreturn.py
vat/gb/moss/resources/return-template.ods
vat/metaphone/__init__.py
vat/metaphone/meta.py
vat/metaphone/metaphone.py
vat/metaphone/word.py