Metadata-Version: 1.1
Name: vat
Version: 0.3.3
Summary: A python package for dealing with VAT
Home-page: http://bitbucket.org/al45tair/vat
Author: Alastair Houghton
Author-email: alastair@alastairs-place.net
License: MIT License
Platform: UNKNOWN
Classifier: Development Status :: 4 - Beta
Classifier: License :: OSI Approved :: MIT License
Classifier: Topic :: Office/Business :: Financial
Provides: vat
